LICENSE
MANIFEST.in
readme.md
setup.py
cached_requests/__init__.py
cached_requests/base.py
cached_requests/base.pyi
cached_requests/cloudscraper.py
cached_requests/py.typed
cached_requests/session.py
cached_requests/utils.py
cached_requests/utils.pyi
cached_requests.egg-info/PKG-INFO
cached_requests.egg-info/SOURCES.txt
cached_requests.egg-info/dependency_links.txt
cached_requests.egg-info/requires.txt
cached_requests.egg-info/top_level.txt
cached_requests/backend/__init__.py
cached_requests/backend/base.py
cached_requests/backend/filesystem.py
cached_requests/backend/utils.py